{
  "deals": [
    {
      "id": 1,
      "userId": 1,
      "categoryId": 1,
      "image": "https://i.ebayimg.com/images/g/InoAAOSwnOdhlzKN/s-l300.jpg",
      "title": "Cruis'n Blast (Nintendo Switch)",
      "price": "19.99",
      "originalPrice": "39.99",
      "link": "https://www.ebay.com/itm/194512367093?mkevt=1&mkcid=1&mkrid=711-53200-19255-0&campid=5337259887&toolid=10001&customid=4fba9f8ea22d11eca14e9a5345c674ba0INT",
      "vendor": "Ebay"
    },
    {
      "id": 2,
      "userId": 1,
      "categoryId": 2,
      "image": "https://pisces.bbystatic.com/image2/BestBuy_US/images/products/6453/6453315_sd.jpg;maxHeight=640;maxWidth=550",
      "title": "LG 77 inch C1 Series OLED Smart TV",
      "price": "2,899.99",
      "originalPrice": "2,999.99",
      "link": "https://www.bestbuy.com/site/lg-77-class-c1-series-oled-4k-uhd-smart-webos-tv/6453315.p?skuId=6453315",
      "vendor": "Best Buy"
    },
    {
      "userId": 1,
      "categoryId": 1,
      "image": "https://pisces.bbystatic.com/image2/BestBuy_US/images/products/6468/6468684_sd.jpg;maxHeight=640;maxWidth=550",
      "title": "Marvel's Guardians of the Galaxy - Xbox Series X",
      "price": "29.99",
      "originalPrice": "59.99",
      "link": "https://www.bestbuy.com/site/marvels-guardians-of-the-galaxy-xbox-series-x/6468684.p?skuId=6468684",
      "vendor": "Best Buy",
      "id": 5
    },
    {
      "userId": 1,
      "image": "https://pisces.bbystatic.com/image2/BestBuy_US/images/products/6455/6455171_sd.jpg;maxHeight=640;maxWidth=550",
      "title": "Hisense - 55\" Class U6G Series Quantum ULED 4K UHD Smart Android TV",
      "price": "449.99",
      "originalPrice": "799.99",
      "link": "https://www.bestbuy.com/site/hisense-55-class-u6g-series-quantum-uled-4k-uhd-smart-android-tv/6455171.p?skuId=6455171",
      "vendor": "Best Buy",
      "categoryId": 2,
      "id": 6
    }
  ],
  "users": [
    {
      "id": 1,
      "name": "snagel33",
      "email": "stevennagel@email.com"
    }
  ],
  "categories": [
    {
      "id": 1,
      "name": "Video Games"
    },
    {
      "id": 2,
      "name": "Televisions"
    }
  ]
}